LICENSE
README.md
pyproject.toml
setup.py
happydomain/__init__.py
happydomain/admin.py
happydomain/api.py
happydomain/authuser.py
happydomain/domain.py
happydomain/error.py
happydomain/provider.py
happydomain/service.py
happydomain/zone.py
happydomain.egg-info/PKG-INFO
happydomain.egg-info/SOURCES.txt
happydomain.egg-info/dependency_links.txt
happydomain.egg-info/requires.txt
happydomain.egg-info/top_level.txt